{
  "updated": "2026-02-26T00:00:23.242Z",
  "auto_fetched": true,
  "xrp": {
    "price": 1.43,
    "change_24h": 6.24203382416275,
    "volume_24h": 4850443110.021484,
    "market_cap": 87408832801.97096
  },
  "rlusd": {
    "market_cap": 1563433553.6583369,
    "source": "coingecko"
  },
  "etf": {
    "last_fetched": "2026-02-26T00:00:05.564Z",
    "source": "xrp-insights",
    "as_of_date": "2026-02-24",
    "total_aum": 1103991361.69,
    "total_xrp_locked": 792221431.6603999,
    "daily_net_flow": 2235181.669999987,
    "daily_inflow": 2237803.280000001,
    "daily_outflow": 2621.610000014305,
    "flow_date": "2026-02-24",
    "weekly_net_flow": 2005017.5177999511,
    "weekly_inflow": 5114268.399999976,
    "weekly_outflow": 3109250.882200025,
    "weekly_start_date": "2026-02-18",
    "cum_net_flow": 19029713.373899966,
    "cum_inflow": 32801391.152299978,
    "funds": [
      {
        "ticker": "XRPC",
        "issuer": "Canary Capital",
        "aum": 260157861.69,
        "xrp_locked": 191375005.48,
        "daily_flow": -2621.610000014305
      },
      {
        "ticker": "XRP",
        "issuer": "Bitwise",
        "aum": 256040570.19,
        "xrp_locked": 188353762.2,
        "daily_flow": 2237803.280000001
      },
      {
        "ticker": "XRPZ",
        "issuer": "Franklin Templeton",
        "aum": 225155423.73,
        "xrp_locked": 165633403.76,
        "daily_flow": 0
      },
      {
        "ticker": "TOXR",
        "issuer": "21Shares",
        "aum": 167058785.08,
        "xrp_locked": 122971034.88,
        "daily_flow": 0
      },
      {
        "ticker": "XRPR",
        "issuer": "REX-Osprey",
        "aum": 88368750,
        "xrp_locked": 45862550,
        "daily_flow": 0
      },
      {
        "ticker": "GXRP",
        "issuer": "Grayscale",
        "aum": 72697760,
        "xrp_locked": 53549640.3404,
        "daily_flow": 0
      },
      {
        "ticker": "BITW",
        "issuer": "Bitwise Index",
        "aum": 34512211,
        "xrp_locked": 24476035,
        "daily_flow": 0
      }
    ],
    "pct_supply": 1.296,
    "circ_supply": 61125057903,
    "num_funds": 7
  },
  "btc_etf": {
    "last_fetched": "2026-02-26T00:00:05.823Z",
    "source": "ishares-ibit",
    "ticker": "IBIT",
    "as_of_date": "2026-02-24",
    "total_aum": 48630658269.74,
    "shares_outstanding": 1332080000,
    "nav_per_share": 36.50731057424479,
    "daily_flow": -116823393.83758333,
    "weekly_net_flow": -54718908.39093004,
    "daily_flow_history": [
      {
        "date": "2026-02-20",
        "flow": 0
      },
      {
        "date": "2026-02-23",
        "flow": 62104485.44665329
      },
      {
        "date": "2026-02-24",
        "flow": -116823393.83758333
      }
    ]
  },
  "eth_etf": {
    "last_fetched": "2026-02-26T00:00:05.816Z",
    "source": "ishares-etha",
    "ticker": "ETHA",
    "as_of_date": "2026-02-24",
    "total_aum": 5822101591.02,
    "shares_outstanding": 414560000,
    "nav_per_share": 14.044050537967967,
    "daily_flow": -45502723.74301621,
    "weekly_net_flow": -43807633.10322205,
    "daily_flow_history": [
      {
        "date": "2026-02-20",
        "flow": 0
      },
      {
        "date": "2026-02-23",
        "flow": 1695090.63979416
      },
      {
        "date": "2026-02-24",
        "flow": -45502723.74301621
      }
    ]
  },
  "supply": {
    "last_fetched": "2026-02-26T00:00:06.713Z",
    "source": "xrp-insights",
    "total_supply": 100000000000,
    "circ_supply": 63075832961,
    "escrow": 36895592731,
    "exchanges": 14167800518.51,
    "defi_total": 197519513.64,
    "corp_treasuries": 473276430,
    "amm_locked": 8750000,
    "xrp_burned": 14287104
  },
  "xrpl_metrics": {
    "last_fetched": "2026-02-26T00:00:06.691Z",
    "source": "xrpl_native",
    "current_ledger": 102495587,
    "last_ledger_txns": 158,
    "avg_tx_per_ledger": 103,
    "fee_burn_per_ledger_xrp": 0.01,
    "book_depth_xrp_usd": {
      "pair": "XRP/USD.GateHub",
      "bids": 10,
      "asks": 10,
      "total_bid_xrp": 163162,
      "total_ask_xrp": 1132629,
      "best_bid": {
        "xrp": 1681.167055,
        "usd": 2427.526991
      },
      "best_ask": {
        "xrp": 2893.841931,
        "usd": 4127.694118
      }
    },
    "dex_volume_24h_usd": null,
    "dex_volume_24h_xrp": null,
    "dex_exchanges_24h": null,
    "dex_takers_24h": null
  },
  "macro": {
    "usd_jpy": 156.20248,
    "jpn_10y": 2.24,
    "us_10y_yield": 4.04,
    "brent_crude": 71.9,
    "fear_greed": {
      "value": 11,
      "label": "Extreme Fear"
    }
  },
  "news": {
    "last_fetched": "2026-02-25T23:41:13.367Z",
    "source": "newsdata",
    "headlines": [
      {
        "title": "XRP Plunges 70%: Can History Bring an 835% Spike?",
        "source": "analyticsinsight",
        "url": "https://www.analyticsinsight.net/xrp/xrp-plunges-70-can-history-bring-an-835-spike",
        "published": "2026-02-25 11:40:34"
      }
    ]
  },
  "manual": {
    "odl_volume_annualized": null,
    "xrp_etf_aum": null,
    "rlusd_circulation": null,
    "permissioned_dex_institutions": null,
    "clarity_act_status": "Pending",
    "_last_manual_update": null
  },
  "kill_switches": {
    "odl_volume": {
      "target": 25000000000,
      "current": null,
      "deadline": "2026-12-31",
      "status": "NEEDS_DATA",
      "pct_complete": null
    },
    "rlusd_circulation": {
      "target": 5000000000,
      "current": 1563433553.6583369,
      "deadline": "2026-12-31",
      "status": "TRACKING",
      "pct_complete": 31
    },
    "xrp_etf_aum": {
      "target": 5000000000,
      "current": 1103991361.69,
      "deadline": "2026-12-31",
      "status": "TRACKING",
      "pct_complete": 22
    },
    "permissioned_dex_adoption": {
      "target_institutions": 5,
      "current": null,
      "deadline": "2026-09-30",
      "status": "NEEDS_DATA"
    },
    "clarity_act": {
      "target": "passed_or_advanced",
      "current": "pending",
      "deadline": "2026-12-31",
      "status": "PENDING"
    }
  },
  "thesis_scores": {
    "regulatory": {
      "status": "CONFIRMED",
      "confidence": "high"
    },
    "institutional_custody": {
      "status": "STRONG",
      "confidence": "high"
    },
    "etf_adoption": {
      "status": "CONFIRMED",
      "confidence": "high"
    },
    "xrpl_infrastructure": {
      "status": "ACCELERATING",
      "confidence": "high"
    },
    "stablecoin_adoption": {
      "status": "GROWING",
      "confidence": "medium"
    },
    "odl_volume": {
      "status": "NEEDS_DATA",
      "confidence": "low"
    },
    "japan_adoption": {
      "status": "FAVORABLE",
      "confidence": "medium"
    },
    "macro_environment": {
      "status": "STRESSED",
      "confidence": "medium"
    }
  },
  "health_check": {
    "xrp": {
      "status": "ok",
      "ts": "2026-02-26T00:00:05.382Z"
    },
    "fear_greed": {
      "status": "ok",
      "ts": "2026-02-26T00:00:05.501Z"
    },
    "etf": {
      "status": "ok",
      "ts": "2026-02-26T00:00:05.564Z"
    },
    "usd_jpy": {
      "status": "ok",
      "ts": "2026-02-26T00:00:05.627Z"
    },
    "etha": {
      "status": "ok",
      "ts": "2026-02-26T00:00:05.817Z"
    },
    "ibit": {
      "status": "ok",
      "ts": "2026-02-26T00:00:05.823Z"
    },
    "rlusd": {
      "status": "ok",
      "ts": "2026-02-26T00:00:06.508Z"
    },
    "xrpl_metrics": {
      "status": "ok",
      "ts": "2026-02-26T00:00:06.691Z"
    },
    "supply": {
      "status": "ok",
      "ts": "2026-02-26T00:00:06.714Z"
    },
    "news": {
      "status": "fail",
      "ts": "2026-02-26T00:00:22.521Z",
      "error": "This operation was aborted"
    },
    "fred_jpn_10y": {
      "status": "ok",
      "ts": "2026-02-26T00:00:22.881Z"
    },
    "fred_brent": {
      "status": "ok",
      "ts": "2026-02-26T00:00:23.058Z"
    },
    "fred_us_10y": {
      "status": "ok",
      "ts": "2026-02-26T00:00:23.242Z"
    }
  },
  "bear_case": {
    "counter_thesis_score": 33,
    "score_reasoning": "Slight reduction from 35 to 33 based on XRP ETF positive flow divergence, but macro stress indicators remain severe and two critical kill switch data gaps (ODL, PermissionedDEX) prevent thesis validation. Bear pressure is structurally unchanged.",
    "competing_infrastructure": [
      {
        "name": "SWIFT GPI",
        "status": "LOW_RISK",
        "status_text": "No material expansion announcements; institutional crypto infrastructure momentum continues to outpace traditional messaging layer upgrades."
      },
      {
        "name": "Visa B2B Connect",
        "status": "LOW_RISK",
        "status_text": "Limited cross-border settlement expansion observed; no direct competitive threat to XRPL bridge utility currently evidenced."
      },
      {
        "name": "JPMorgan Kinexys",
        "status": "MONITORING",
        "status_text": "Established institutional platform with JPM distribution network. Stable but not expanding into XRPL's target corridors. Coexistence model most likely."
      },
      {
        "name": "BIS Project Nexus",
        "status": "ELEVATED_RISK",
        "status_text": "Multi-CBDC interoperability platform remains the most credible structural bypass threat to XRPL's bridge currency thesis. Central bank backing gives it sovereign-grade legitimacy that XRPL cannot match."
      },
      {
        "name": "Ethereum Institutional",
        "status": "MONITORING",
        "status_text": "ETH ETF outflows (-$46M daily, -$44M weekly) indicate institutional confidence erosion. No major settlement infrastructure advances challenging XRPL's niche."
      }
    ],
    "odl_stagnation": "Critical blind spot — zero verifiable ODL volume data available with Q3 2026 transparency deadline approaching. If ODL volume is not growing proportionally to institutional rhetoric, the core utility thesis collapses.",
    "token_velocity_concern": "XRP's +6.8% bounce on extreme fear (F&G: 11) may indicate speculative rather than utility-driven demand; ETF net inflows at only $2.2M are constructive but tiny relative to $1.1B AUM base, suggesting accumulation pace is marginal.",
    "macro_headwinds": [
      {
        "name": "Global Recession Risk",
        "status": "ELEVATED_RISK",
        "status_text": "Fear & Greed at 11 is extreme — near floor levels. Combined with Japan yield crisis and trade escalation, recession risk signals are at their strongest in this monitoring period."
      },
      {
        "name": "Crypto Winter Signals",
        "status": "ELEVATED_RISK",
        "status_text": "BTC ETF outflows of -$117M and ETH ETF outflows of -$46M on same day indicate institutional capital continuing to exit crypto broadly. XRP divergence may be temporary."
      },
      {
        "name": "Regulatory Reversal Risk",
        "status": "LOW_RISK",
        "status_text": "No negative regulatory signals from current administration. Clarity Act pending but no opposition momentum detected. Section 122 framework stable."
      },
      {
        "name": "Rate Hike Extension",
        "status": "MONITORING",
        "status_text": "US 10Y at 4.03% is elevated but stable. JGB 10Y at 2.24% is the primary rate concern — BOJ may be forced into emergency action that could cascade through global rates."
      }
    ],
    "bear_narrative": "The two most critical kill switches — ODL volume and PermissionedDEX institutional count — have zero data with Q3 deadlines approaching. Without verifiable utility growth, XRP's thesis rests entirely on infrastructure buildout and ETF accumulation in an extreme fear environment where BTC and ETH institutional capital is actively exiting. BIS Project Nexus remains the most credible structural alternative that could render XRPL's bridge currency function obsolete at the sovereign level. The XRP ETF flow divergence is real but tiny ($2.2M against $1.1B AUM), and one day of positive flow does not establish a trend against the backdrop of $117M+ outflows from the crypto market's anchor product.",
    "last_updated": "2026-02-25T15:14:04.203Z"
  },
  "probability": {
    "bear": 8,
    "base": 40,
    "mid": 40,
    "bull": 12,
    "last_updated": "2026-02-25T15:14:04.203Z",
    "last_reasoning": "No adjustment recommended. XRP ETF flow divergence is constructive but insufficient to shift probabilities given persistent extreme stress across macro indicators. JGB yields remain critical, F&G at extreme fear floor. The +6.8% XRP bounce needs multi-day confirmation before being treated as a trend reversal signal."
  },
  "last_analysis": {
    "timestamp": "2026-02-25T15:14:04.203Z",
    "run_type": "morning",
    "stress_level": "ELEVATED",
    "stress_score": 80,
    "applied_at": "2026-02-25T16:02:19.733Z",
    "changes_applied": 2
  },
  "x402_agent": {
    "network": "XRPL MAINNET",
    "merchant_address": "r4K5EDq2UPA2J6kecNKuFVAxs65gmfBYZP",
    "protocol": "x402 v2",
    "facilitator": "https://xrpl-facilitator-mainnet.t54.ai",
    "facilitator_ok": true,
    "agent_address": "rPiok45Qs88WMYQbYzDqXQbPgaCr9PnX5M",
    "merchant_base": "http://127.0.0.1:4403",
    "balance_xrp": 14.992917,
    "payments_sent": 6,
    "session_drops_spent": 3000,
    "session_xrp_spent": 0.003,
    "lifetime_drops_spent": 6000,
    "lifetime_xrp_spent": 0.006,
    "guardrails": {
      "balance_floor_xrp": 11,
      "session_cap_drops": 10000,
      "max_single_drops": 5000
    },
    "transactions": [
      {
        "endpoint": "/api/v1/premium-analysis",
        "label": "Premium Analysis",
        "pay_to": "r4K5EDq2UPA2J6kecNKuFVAxs65gmfBYZP",
        "amount_drops": "1000",
        "amount_xrp": 0.001,
        "invoice_id": "BA32A9D5E1244E688AC8BDD38026563F",
        "tx_hash": "F05D4EEFD82F66C34E22277C4606BBBA239CA41A3CE60894641811F4EC042E8B",
        "status": "SUCCESS",
        "timestamp": "2026-02-25T16:40:22.429Z"
      },
      {
        "endpoint": "/api/v1/bear-case",
        "label": "Bear Case",
        "pay_to": "r4K5EDq2UPA2J6kecNKuFVAxs65gmfBYZP",
        "amount_drops": "1500",
        "amount_xrp": 0.0015,
        "invoice_id": "8FAF4ECC30B74AB4AC7A693401978F36",
        "tx_hash": "E0145699EF5C2359EDC68EABE52BC24C657B755D23BEBE7AA9FE1F423A9DD053",
        "status": "SUCCESS",
        "timestamp": "2026-02-25T16:40:30.104Z"
      },
      {
        "endpoint": "/api/v1/stress-report",
        "label": "Stress Report",
        "pay_to": "r4K5EDq2UPA2J6kecNKuFVAxs65gmfBYZP",
        "amount_drops": "500",
        "amount_xrp": 0.0005,
        "invoice_id": "47FF0ADFEE494D3187949F3944E5EB53",
        "tx_hash": "307340511901488A87DC7AC07A83FAAF3274DD0DD1D0B3CB717515CC7626F423",
        "status": "SUCCESS",
        "timestamp": "2026-02-25T16:40:37.784Z"
      }
    ],
    "last_payment": {
      "endpoint": "/api/v1/stress-report",
      "label": "Stress Report",
      "pay_to": "r4K5EDq2UPA2J6kecNKuFVAxs65gmfBYZP",
      "amount_drops": "500",
      "amount_xrp": 0.0005,
      "invoice_id": "47FF0ADFEE494D3187949F3944E5EB53",
      "tx_hash": "307340511901488A87DC7AC07A83FAAF3274DD0DD1D0B3CB717515CC7626F423",
      "status": "SUCCESS",
      "timestamp": "2026-02-25T16:40:37.784Z"
    },
    "x402_flow": [
      "── Premium Analysis ──",
      "→ GET http://127.0.0.1:4403/api/v1/premium-analysis  →  HTTP 402",
      "← 402  amount=1000 drops  invoiceId=BA32A9D5E124…",
      "→ Signed Payment  hash=F05D4EEFD82F…  drops=1000",
      "→ GET (+PAYMENT-SIGNATURE)  →  HTTP 200",
      "← 200  tx=F05D4EEFD82F…  payer=rPiok45Qs8…",
      "── Bear Case ──",
      "→ GET http://127.0.0.1:4403/api/v1/bear-case  →  HTTP 402",
      "← 402  amount=1500 drops  invoiceId=8FAF4ECC30B7…",
      "→ Signed Payment  hash=E0145699EF5C…  drops=1500",
      "→ GET (+PAYMENT-SIGNATURE)  →  HTTP 200",
      "← 200  tx=E0145699EF5C…  payer=rPiok45Qs8…",
      "── Stress Report ──",
      "→ GET http://127.0.0.1:4403/api/v1/stress-report  →  HTTP 402",
      "← 402  amount=500 drops  invoiceId=47FF0ADFEE49…",
      "→ Signed Payment  hash=307340511901…  drops=500",
      "→ GET (+PAYMENT-SIGNATURE)  →  HTTP 200",
      "← 200  tx=307340511901…  payer=rPiok45Qs8…"
    ],
    "last_updated": "2026-02-25T16:40:38.167Z"
  }
}